kalpaa/__init__.py
kalpaa/common/__init__.py
kalpaa/common/angles.py
kalpaa/common/cli_utils.py
kalpaa/common/model_params.py
kalpaa/common/runner_utils.py
kalpaa/completions/__init__.py
kalpaa/config/__init__.py
kalpaa/config/config.py
kalpaa/config/config_reader.py
kalpaa/inference_coalesce/__init__.py
kalpaa/inference_coalesce/coalescer.py
kalpaa/meta.py
kalpaa/py.typed
kalpaa/read_bin_csv.py
kalpaa/stages/__init__.py
kalpaa/stages/stage01.py
kalpaa/stages/stage02.py
kalpaa/stages/stage03.py
kalpaa/stages/stage03_1.py
kalpaa/stages/stage04.py
kalpaa-1.2.0.dist-info/METADATA
kalpaa-1.2.0.dist-info/WHEEL
kalpaa-1.2.0.dist-info/entry_points.txt
kalpaa-1.2.0.dist-info/RECORD
