Metadata-Version: 2.1
Name: kalpaa
Version: 1.2.0
Summary: Groups up and runs full run.
Author: Deepak Mallubhotla
Author-email: dmallubhotla+github@gmail.com
Requires-Python: >=3.8.1,<3.10
Classifier: Programming Language :: Python :: 3
Classifier: Programming Language :: Python :: 3.9
Requires-Dist: dacite (>=1.9.2,<2.0.0)
Requires-Dist: deepdog (>=1.5.0,<2.0.0)
Requires-Dist: pdme (>=1.5.0,<2.0.0)
Requires-Dist: tantri (>=1.3.0,<2.0.0)
Requires-Dist: tomli (>=2.0.1,<3.0.0)
